ndex_examples/__init__.py
ndex_examples/merge/__init__.py
ndex_examples/merge/bindingdb_merger.py
ndex_examples/merge/example_script.py
ndex_examples/merge/scratch_test.py
ndex_examples-1.0.0.dev6.dist-info/DESCRIPTION.rst
ndex_examples-1.0.0.dev6.dist-info/METADATA
ndex_examples-1.0.0.dev6.dist-info/metadata.json
ndex_examples-1.0.0.dev6.dist-info/RECORD
ndex_examples-1.0.0.dev6.dist-info/top_level.txt
ndex_examples-1.0.0.dev6.dist-info/WHEEL
