Metadata-Version: 2.0
Name: ndex-examples
Version: 1.0.0.dev6
Summary: These example illustrate the use of NDEx from Python.
Home-page: https://www.ndexbio.org
Author: The NDEx Project
Author-email: contact@ndexbio.org
License: BSD
Keywords: network analysis biology
Platform: UNKNOWN
Classifier: Development Status :: 2 - Pre-Alpha
Classifier: Intended Audience :: Science/Research
Classifier: Topic :: Scientific/Engineering :: Information Analysis
Classifier: Topic :: Scientific/Engineering :: Bio-Informatics
Classifier: Topic :: Scientific/Engineering :: Medical Science Apps.
Classifier: License :: OSI Approved :: BSD License
Classifier: Programming Language :: Python :: 2.7
